{"trial_id": "0010", "hyperparameters": {"space": [{"class_name": "Choice", "config": {"name": "n_neuron_indx", "default": 0, "conditions": [], "values": [0, 1, 2], "ordered": true}}, {"class_name": "Choice", "config": {"name": "optimizer", "default": "adam", "conditions": [], "values": ["adam", "rmsprop"], "ordered": false}}, {"class_name": "Choice", "config": {"name": "learning_rate", "default": 0.0005, "conditions": [], "values": [0.0005, 0.001], "ordered": true}}], "values": {"n_neuron_indx": 2, "optimizer": "rmsprop", "learning_rate": 0.0005}}, "metrics": {"metrics": {"loss": {"direction": "min", "observations": [{"value": [0.010652600787580013], "step": 12}]}, "mae": {"direction": "min", "observations": [{"value": [0.06708788871765137], "step": 12}]}, "val_loss": {"direction": "min", "observations": [{"value": [0.013667222112417221], "step": 12}]}, "val_mae": {"direction": "min", "observations": [{"value": [0.06753811240196228], "step": 12}]}}}, "score": 0.013667222112417221, "best_step": 12, "status": "COMPLETED", "message": null}